{
  "contributors": null,
  "coordinates": null,
  "created_at": "Wed Jun 10 12:32:03 +0000 2020",
  "display_text_range": [
    0,
    140
  ],
  "entities": {
    "hashtags": [],
    "symbols": [],
    "urls": [],
    "user_mentions": [
      {
        "id": 930552552302792705,
        "id_str": "930552552302792705",
        "indices": [
          3,
          17
        ],
        "name": "Dan Crenshaw",
        "screen_name": "DanCrenshawTX"
      }
    ]
  },
  "favorite_count": 0,
  "favorited": false,
  "full_text": "RT @DanCrenshawTX: This is dangerous, counterproductive, and deeply irrational. \u201cDefund the police\u201d is not a call from the fringes of the f\u2026",
  "geo": null,
  "id": 1270695218397040640,
  "id_str": "1270695218397040640",
  "in_reply_to_screen_name": null,
  "in_reply_to_status_id": null,
  "in_reply_to_status_id_str": null,
  "in_reply_to_user_id": null,
  "in_reply_to_user_id_str": null,
  "is_quote_status": true,
  "lang": "en",
  "place": null,
  "quoted_status_id": 1269756548416495617,
  "quoted_status_id_str": "1269756548416495617",
  "quoted_status_permalink": {
    "display": "twitter.com/cnnbrk/status/\u2026",
    "expanded": "https://twitter.com/cnnbrk/status/1269756548416495617",
    "url": "https://t.co/sLAqYADbaw"
  },
  "retweet_count": 8994,
  "retweeted": false,
  "retweeted_status": {
    "contributors": null,
    "coordinates": null,
    "created_at": "Mon Jun 08 00:59:09 +0000 2020",
    "display_text_range": [
      0,
      226
    ],
    "entities": {
      "hashtags": [],
      "symbols": [],
      "urls": [
        {
          "display_url": "twitter.com/cnnbrk/status/\u2026",
          "expanded_url": "https://twitter.com/cnnbrk/status/1269756548416495617",
          "indices": [
            227,
            250
          ],
          "url": "https://t.co/sLAqYADbaw"
        }
      ],
      "user_mentions": []
    },
    "favorite_count": 29790,
    "favorited": false,
    "full_text": "This is dangerous, counterproductive, and deeply irrational. \u201cDefund the police\u201d is not a call from the fringes of the far left anymore. It has gone from a radical slogan to actual policy in a major American city, within days. https://t.co/sLAqYADbaw",
    "geo": null,
    "id": 1269796072425050112,
    "id_str": "1269796072425050112",
    "in_reply_to_screen_name": null,
    "in_reply_to_status_id": null,
    "in_reply_to_status_id_str": null,
    "in_reply_to_user_id": null,
    "in_reply_to_user_id_str": null,
    "is_quote_status": true,
    "lang": "en",
    "place": null,
    "possibly_sensitive": false,
    "quoted_status": {
      "contributors": null,
      "coordinates": null,
      "created_at": "Sun Jun 07 22:22:06 +0000 2020",
      "display_text_range": [
        0,
        172
      ],
      "entities": {
        "hashtags": [],
        "media": [
          {
            "display_url": "pic.twitter.com/NG6C0lJfyC",
            "expanded_url": "https://twitter.com/cnnbrk/status/1269756548416495617/photo/1",
            "id": 1269756546705170432,
            "id_str": "1269756546705170432",
            "indices": [
              173,
              196
            ],
            "media_url": "http://pbs.twimg.com/media/EZ8U2g2WoAAPU2t.jpg",
            "media_url_https": "https://pbs.twimg.com/media/EZ8U2g2WoAAPU2t.jpg",
            "sizes": {
              "large": {
                "h": 360,
                "resize": "fit",
                "w": 640
              },
              "medium": {
                "h": 360,
                "resize": "fit",
                "w": 640
              },
              "small": {
                "h": 360,
                "resize": "fit",
                "w": 640
              },
              "thumb": {
                "h": 150,
                "resize": "crop",
                "w": 150
              }
            },
            "type": "photo",
            "url": "https://t.co/NG6C0lJfyC"
          }
        ],
        "symbols": [],
        "urls": [
          {
            "display_url": "cnn.it/2XEjVtu",
            "expanded_url": "https://cnn.it/2XEjVtu",
            "indices": [
              149,
              172
            ],
            "url": "https://t.co/mAWBGAn5Pd"
          }
        ],
        "user_mentions": []
      },
      "extended_entities": {
        "media": [
          {
            "display_url": "pic.twitter.com/NG6C0lJfyC",
            "expanded_url": "https://twitter.com/cnnbrk/status/1269756548416495617/photo/1",
            "id": 1269756546705170432,
            "id_str": "1269756546705170432",
            "indices": [
              173,
              196
            ],
            "media_url": "http://pbs.twimg.com/media/EZ8U2g2WoAAPU2t.jpg",
            "media_url_https": "https://pbs.twimg.com/media/EZ8U2g2WoAAPU2t.jpg",
            "sizes": {
              "large": {
                "h": 360,
                "resize": "fit",
                "w": 640
              },
              "medium": {
                "h": 360,
                "resize": "fit",
                "w": 640
              },
              "small": {
                "h": 360,
                "resize": "fit",
                "w": 640
              },
              "thumb": {
                "h": 150,
                "resize": "crop",
                "w": 150
              }
            },
            "type": "photo",
            "url": "https://t.co/NG6C0lJfyC"
          }
        ]
      },
      "favorite_count": 11649,
      "favorited": false,
      "full_text": "Nine members of Minneapolis' city council \u2014 a veto-proof majority \u2014 say they'll start the process of defunding and dismantling the police department\nhttps://t.co/mAWBGAn5Pd https://t.co/NG6C0lJfyC",
      "geo": null,
      "id": 1269756548416495617,
      "id_str": "1269756548416495617",
      "in_reply_to_screen_name": null,
      "in_reply_to_status_id": null,
      "in_reply_to_status_id_str": null,
      "in_reply_to_user_id": null,
      "in_reply_to_user_id_str": null,
      "is_quote_status": false,
      "lang": "en",
      "place": null,
      "possibly_sensitive": false,
      "retweet_count": 3239,
      "retweeted": false,
      "source": "<a href=\"http://www.socialflow.com\" rel=\"nofollow\">SocialFlow</a>",
      "truncated": false,
      "user": {
        "contributors_enabled": false,
        "created_at": "Tue Jan 02 01:48:14 +0000 2007",
        "default_profile": false,
        "default_profile_image": false,
        "description": "Breaking news from CNN Digital. Now 57M strong. Check @cnn for all things CNN, breaking and more. Download the app for custom alerts: https://t.co/UCHG9M367J",
        "entities": {
          "description": {
            "urls": [
              {
                "display_url": "cnn.com/apps",
                "expanded_url": "http://cnn.com/apps",
                "indices": [
                  134,
                  157
                ],
                "url": "https://t.co/UCHG9M367J"
              }
            ]
          },
          "url": {
            "urls": [
              {
                "display_url": "cnn.com",
                "expanded_url": "http://cnn.com/",
                "indices": [
                  0,
                  22
                ],
                "url": "http://t.co/HjKR4r61U5"
              }
            ]
          }
        },
        "favourites_count": 21,
        "follow_request_sent": false,
        "followers_count": 57985400,
        "following": false,
        "friends_count": 119,
        "geo_enabled": false,
        "has_extended_profile": false,
        "id": 428333,
        "id_str": "428333",
        "is_translation_enabled": true,
        "is_translator": false,
        "lang": null,
        "listed_count": 181389,
        "location": "Everywhere",
        "name": "CNN Breaking News",
        "notifications": false,
        "profile_background_color": "323232",
        "profile_background_image_url": "http://abs.twimg.com/images/themes/theme1/bg.png",
        "profile_background_image_url_https": "https://abs.twimg.com/images/themes/theme1/bg.png",
        "profile_background_tile": false,
        "profile_banner_url": "https://pbs.twimg.com/profile_banners/428333/1531855520",
        "profile_image_url": "http://pbs.twimg.com/profile_images/925092227667304448/fAY1HUu3_normal.jpg",
        "profile_image_url_https": "https://pbs.twimg.com/profile_images/925092227667304448/fAY1HUu3_normal.jpg",
        "profile_link_color": "004287",
        "profile_sidebar_border_color": "DADADA",
        "profile_sidebar_fill_color": "EEEEEE",
        "profile_text_color": "000000",
        "profile_use_background_image": true,
        "protected": false,
        "screen_name": "cnnbrk",
        "statuses_count": 71027,
        "time_zone": null,
        "translator_type": "regular",
        "url": "http://t.co/HjKR4r61U5",
        "utc_offset": null,
        "verified": true
      }
    },
    "quoted_status_id": 1269756548416495617,
    "quoted_status_id_str": "1269756548416495617",
    "quoted_status_permalink": {
      "display": "twitter.com/cnnbrk/status/\u2026",
      "expanded": "https://twitter.com/cnnbrk/status/1269756548416495617",
      "url": "https://t.co/sLAqYADbaw"
    },
    "retweet_count": 8994,
    "retweeted": false,
    "source": "<a href=\"http://twitter.com/download/iphone\" rel=\"nofollow\">Twitter for iPhone</a>",
    "truncated": false,
    "user": {
      "contributors_enabled": false,
      "created_at": "Tue Nov 14 21:46:32 +0000 2017",
      "default_profile": false,
      "default_profile_image": false,
      "description": "Dan Crenshaw, Congressman, Lieutenant Commander (Ret), a former Navy SEAL.",
      "entities": {
        "description": {
          "urls": []
        }
      },
      "favourites_count": 1138,
      "follow_request_sent": false,
      "followers_count": 934369,
      "following": false,
      "friends_count": 813,
      "geo_enabled": false,
      "has_extended_profile": false,
      "id": 930552552302792705,
      "id_str": "930552552302792705",
      "is_translation_enabled": false,
      "is_translator": false,
      "lang": null,
      "listed_count": 2074,
      "location": "Houston, TX",
      "name": "Dan Crenshaw",
      "notifications": false,
      "profile_background_color": "000000",
      "profile_background_image_url": "http://abs.twimg.com/images/themes/theme1/bg.png",
      "profile_background_image_url_https": "https://abs.twimg.com/images/themes/theme1/bg.png",
      "profile_background_tile": false,
      "profile_banner_url": "https://pbs.twimg.com/profile_banners/930552552302792705/1541634921",
      "profile_image_url": "http://pbs.twimg.com/profile_images/1047938321186480128/GF8q1URJ_normal.jpg",
      "profile_image_url_https": "https://pbs.twimg.com/profile_images/1047938321186480128/GF8q1URJ_normal.jpg",
      "profile_link_color": "FAB81E",
      "profile_sidebar_border_color": "000000",
      "profile_sidebar_fill_color": "000000",
      "profile_text_color": "000000",
      "profile_use_background_image": false,
      "protected": false,
      "screen_name": "DanCrenshawTX",
      "statuses_count": 1640,
      "time_zone": null,
      "translator_type": "none",
      "url": null,
      "utc_offset": null,
      "verified": true
    }
  },
  "source": "<a href=\"http://twitter.com/download/iphone\" rel=\"nofollow\">Twitter for iPhone</a>",
  "truncated": false,
  "user": {
    "contributors_enabled": false,
    "created_at": "Wed Mar 18 13:46:38 +0000 2009",
    "default_profile": false,
    "default_profile_image": false,
    "description": "45th President of the United States of America\ud83c\uddfa\ud83c\uddf8",
    "entities": {
      "description": {
        "urls": []
      },
      "url": {
        "urls": [
          {
            "display_url": "Instagram.com/realDonaldTrump",
            "expanded_url": "http://www.Instagram.com/realDonaldTrump",
            "indices": [
              0,
              23
            ],
            "url": "https://t.co/OMxB0x7xC5"
          }
        ]
      }
    },
    "favourites_count": 5,
    "follow_request_sent": false,
    "followers_count": 81998699,
    "following": true,
    "friends_count": 46,
    "geo_enabled": true,
    "has_extended_profile": false,
    "id": 25073877,
    "id_str": "25073877",
    "is_translation_enabled": true,
    "is_translator": false,
    "lang": null,
    "listed_count": 115143,
    "location": "Washington, DC",
    "name": "Donald J. Trump",
    "notifications": false,
    "profile_background_color": "6D5C18",
    "profile_background_image_url": "http://abs.twimg.com/images/themes/theme1/bg.png",
    "profile_background_image_url_https": "https://abs.twimg.com/images/themes/theme1/bg.png",
    "profile_background_tile": true,
    "profile_banner_url": "https://pbs.twimg.com/profile_banners/25073877/1583212785",
    "profile_image_url": "http://pbs.twimg.com/profile_images/874276197357596672/kUuht00m_normal.jpg",
    "profile_image_url_https": "https://pbs.twimg.com/profile_images/874276197357596672/kUuht00m_normal.jpg",
    "profile_link_color": "1B95E0",
    "profile_sidebar_border_color": "BDDCAD",
    "profile_sidebar_fill_color": "C5CEC0",
    "profile_text_color": "333333",
    "profile_use_background_image": true,
    "protected": false,
    "screen_name": "realDonaldTrump",
    "statuses_count": 52764,
    "time_zone": null,
    "translator_type": "regular",
    "url": "https://t.co/OMxB0x7xC5",
    "utc_offset": null,
    "verified": true
  }
}