{
  "contributors": null,
  "coordinates": null,
  "created_at": "Sat Jul 18 04:39:30 +0000 2020",
  "display_text_range": [
    0,
    140
  ],
  "entities": {
    "hashtags": [],
    "symbols": [],
    "urls": [],
    "user_mentions": [
      {
        "id": 119837703,
        "id_str": "119837703",
        "indices": [
          3,
          15
        ],
        "name": "Chuck Ross",
        "screen_name": "ChuckRossDC"
      }
    ]
  },
  "favorite_count": 0,
  "favorited": false,
  "full_text": "RT @ChuckRossDC: I know there's no connection between this op-ed and WaPo taking $4.6 million from Chinese foreign agent China Daily for pa\u2026",
  "geo": null,
  "id": 1284347039195762688,
  "id_str": "1284347039195762688",
  "in_reply_to_screen_name": null,
  "in_reply_to_status_id": null,
  "in_reply_to_status_id_str": null,
  "in_reply_to_user_id": null,
  "in_reply_to_user_id_str": null,
  "is_quote_status": true,
  "lang": "en",
  "place": null,
  "quoted_status_id": 1283502480031088642,
  "quoted_status_id_str": "1283502480031088642",
  "quoted_status_permalink": {
    "display": "twitter.com/washingtonpost\u2026",
    "expanded": "https://twitter.com/washingtonpost/status/1283502480031088642",
    "url": "https://t.co/gmCVLrakcf"
  },
  "retweet_count": 4488,
  "retweeted": false,
  "retweeted_status": {
    "contributors": null,
    "coordinates": null,
    "created_at": "Wed Jul 15 20:54:18 +0000 2020",
    "display_text_range": [
      0,
      231
    ],
    "entities": {
      "hashtags": [],
      "symbols": [],
      "urls": [
        {
          "display_url": "twitter.com/washingtonpost\u2026",
          "expanded_url": "https://twitter.com/washingtonpost/status/1283502480031088642",
          "indices": [
            208,
            231
          ],
          "url": "https://t.co/gmCVLrakcf"
        }
      ],
      "user_mentions": []
    },
    "favorite_count": 9390,
    "favorited": false,
    "full_text": "I know there's no connection between this op-ed and WaPo taking $4.6 million from Chinese foreign agent China Daily for paid advertorials....but WaPo took $4.6 million from China Daily for paid advertorials. https://t.co/gmCVLrakcf",
    "geo": null,
    "id": 1283505189622878215,
    "id_str": "1283505189622878215",
    "in_reply_to_screen_name": null,
    "in_reply_to_status_id": null,
    "in_reply_to_status_id_str": null,
    "in_reply_to_user_id": null,
    "in_reply_to_user_id_str": null,
    "is_quote_status": true,
    "lang": "en",
    "place": null,
    "possibly_sensitive": false,
    "quoted_status": {
      "contributors": null,
      "coordinates": null,
      "created_at": "Wed Jul 15 20:43:32 +0000 2020",
      "display_text_range": [
        0,
        93
      ],
      "entities": {
        "hashtags": [],
        "symbols": [],
        "urls": [
          {
            "display_url": "wapo.st/38Wlxmq",
            "expanded_url": "https://wapo.st/38Wlxmq",
            "indices": [
              70,
              93
            ],
            "url": "https://t.co/E2mzkfnpg6"
          }
        ],
        "user_mentions": []
      },
      "favorite_count": 2786,
      "favorited": false,
      "full_text": "Opinion: I\u2019m from Wuhan. I got covid-19 \u2014 after traveling to Florida. https://t.co/E2mzkfnpg6",
      "geo": null,
      "id": 1283502480031088642,
      "id_str": "1283502480031088642",
      "in_reply_to_screen_name": null,
      "in_reply_to_status_id": null,
      "in_reply_to_status_id_str": null,
      "in_reply_to_user_id": null,
      "in_reply_to_user_id_str": null,
      "is_quote_status": false,
      "lang": "en",
      "place": null,
      "possibly_sensitive": false,
      "retweet_count": 935,
      "retweeted": false,
      "source": "<a href=\"http://www.socialflow.com\" rel=\"nofollow\">SocialFlow</a>",
      "truncated": false,
      "user": {
        "contributors_enabled": false,
        "created_at": "Tue Mar 27 11:19:39 +0000 2007",
        "default_profile": false,
        "default_profile_image": false,
        "description": "Breaking news, analysis, and opinion. Founded in 1877. Our staff on Twitter: https://t.co/VV0UBAMHg8",
        "entities": {
          "description": {
            "urls": [
              {
                "display_url": "twitter.com/washingtonpost\u2026",
                "expanded_url": "https://twitter.com/washingtonpost/lists/washington-post-people",
                "indices": [
                  77,
                  100
                ],
                "url": "https://t.co/VV0UBAMHg8"
              }
            ]
          },
          "url": {
            "urls": [
              {
                "display_url": "washingtonpost.com",
                "expanded_url": "http://washingtonpost.com",
                "indices": [
                  0,
                  22
                ],
                "url": "http://t.co/Hq7hTYkOPg"
              }
            ]
          }
        },
        "favourites_count": 4437,
        "follow_request_sent": false,
        "followers_count": 16110715,
        "following": false,
        "friends_count": 1656,
        "geo_enabled": true,
        "has_extended_profile": false,
        "id": 2467791,
        "id_str": "2467791",
        "is_translation_enabled": true,
        "is_translator": false,
        "lang": null,
        "listed_count": 94037,
        "location": "Washington, DC",
        "name": "The Washington Post",
        "notifications": false,
        "profile_background_color": "333333",
        "profile_background_image_url": "http://abs.twimg.com/images/themes/theme1/bg.png",
        "profile_background_image_url_https": "https://abs.twimg.com/images/themes/theme1/bg.png",
        "profile_background_tile": false,
        "profile_banner_url": "https://pbs.twimg.com/profile_banners/2467791/1469484132",
        "profile_image_url": "http://pbs.twimg.com/profile_images/1060271522319925257/fJKwJ0r2_normal.jpg",
        "profile_image_url_https": "https://pbs.twimg.com/profile_images/1060271522319925257/fJKwJ0r2_normal.jpg",
        "profile_link_color": "0057EC",
        "profile_sidebar_border_color": "FFFFFF",
        "profile_sidebar_fill_color": "DBDBDB",
        "profile_text_color": "323232",
        "profile_use_background_image": true,
        "protected": false,
        "screen_name": "washingtonpost",
        "statuses_count": 364718,
        "time_zone": null,
        "translator_type": "regular",
        "url": "http://t.co/Hq7hTYkOPg",
        "utc_offset": null,
        "verified": true
      }
    },
    "quoted_status_id": 1283502480031088642,
    "quoted_status_id_str": "1283502480031088642",
    "quoted_status_permalink": {
      "display": "twitter.com/washingtonpost\u2026",
      "expanded": "https://twitter.com/washingtonpost/status/1283502480031088642",
      "url": "https://t.co/gmCVLrakcf"
    },
    "retweet_count": 4488,
    "retweeted": false,
    "source": "<a href=\"https://mobile.twitter.com\" rel=\"nofollow\">Twitter Web App</a>",
    "truncated": false,
    "user": {
      "contributors_enabled": false,
      "created_at": "Thu Mar 04 20:00:53 +0000 2010",
      "default_profile": false,
      "default_profile_image": false,
      "description": "Reporter at The Daily Caller News Foundation -- email tips securely to chuck.ross@protonmail.com",
      "entities": {
        "description": {
          "urls": []
        },
        "url": {
          "urls": [
            {
              "display_url": "dailycaller.com",
              "expanded_url": "http://dailycaller.com",
              "indices": [
                0,
                23
              ],
              "url": "https://t.co/hXbunu1TI5"
            }
          ]
        }
      },
      "favourites_count": 8320,
      "follow_request_sent": false,
      "followers_count": 131654,
      "following": false,
      "friends_count": 305,
      "geo_enabled": true,
      "has_extended_profile": false,
      "id": 119837703,
      "id_str": "119837703",
      "is_translation_enabled": false,
      "is_translator": false,
      "lang": null,
      "listed_count": 1157,
      "location": "",
      "name": "Chuck Ross",
      "notifications": false,
      "profile_background_color": "022330",
      "profile_background_image_url": "http://abs.twimg.com/images/themes/theme15/bg.png",
      "profile_background_image_url_https": "https://abs.twimg.com/images/themes/theme15/bg.png",
      "profile_background_tile": false,
      "profile_banner_url": "https://pbs.twimg.com/profile_banners/119837703/1519594720",
      "profile_image_url": "http://pbs.twimg.com/profile_images/1168884848074874880/I3MywMxl_normal.jpg",
      "profile_image_url_https": "https://pbs.twimg.com/profile_images/1168884848074874880/I3MywMxl_normal.jpg",
      "profile_link_color": "0084B4",
      "profile_sidebar_border_color": "A8C7F7",
      "profile_sidebar_fill_color": "C0DFEC",
      "profile_text_color": "333333",
      "profile_use_background_image": true,
      "protected": false,
      "screen_name": "ChuckRossDC",
      "statuses_count": 61945,
      "time_zone": null,
      "translator_type": "none",
      "url": "https://t.co/hXbunu1TI5",
      "utc_offset": null,
      "verified": true
    }
  },
  "source": "<a href=\"http://twitter.com/download/iphone\" rel=\"nofollow\">Twitter for iPhone</a>",
  "truncated": false,
  "user": {
    "contributors_enabled": false,
    "created_at": "Wed Mar 18 13:46:38 +0000 2009",
    "default_profile": false,
    "default_profile_image": false,
    "description": "45th President of the United States of America\ud83c\uddfa\ud83c\uddf8",
    "entities": {
      "description": {
        "urls": []
      },
      "url": {
        "urls": [
          {
            "display_url": "Instagram.com/realDonaldTrump",
            "expanded_url": "http://www.Instagram.com/realDonaldTrump",
            "indices": [
              0,
              23
            ],
            "url": "https://t.co/OMxB0x7xC5"
          }
        ]
      }
    },
    "favourites_count": 4,
    "follow_request_sent": false,
    "followers_count": 83705352,
    "following": true,
    "friends_count": 46,
    "geo_enabled": true,
    "has_extended_profile": false,
    "id": 25073877,
    "id_str": "25073877",
    "is_translation_enabled": true,
    "is_translator": false,
    "lang": null,
    "listed_count": 116779,
    "location": "Washington, DC",
    "name": "Donald J. Trump",
    "notifications": false,
    "profile_background_color": "6D5C18",
    "profile_background_image_url": "http://abs.twimg.com/images/themes/theme1/bg.png",
    "profile_background_image_url_https": "https://abs.twimg.com/images/themes/theme1/bg.png",
    "profile_background_tile": true,
    "profile_banner_url": "https://pbs.twimg.com/profile_banners/25073877/1595058372",
    "profile_image_url": "http://pbs.twimg.com/profile_images/874276197357596672/kUuht00m_normal.jpg",
    "profile_image_url_https": "https://pbs.twimg.com/profile_images/874276197357596672/kUuht00m_normal.jpg",
    "profile_link_color": "1B95E0",
    "profile_sidebar_border_color": "BDDCAD",
    "profile_sidebar_fill_color": "C5CEC0",
    "profile_text_color": "333333",
    "profile_use_background_image": true,
    "protected": false,
    "screen_name": "realDonaldTrump",
    "statuses_count": 53770,
    "time_zone": null,
    "translator_type": "regular",
    "url": "https://t.co/OMxB0x7xC5",
    "utc_offset": null,
    "verified": true
  }
}