{
  "contributors": null,
  "coordinates": null,
  "created_at": "Tue Dec 01 23:55:55 +0000 2020",
  "display_text_range": [
    0,
    140
  ],
  "entities": {
    "hashtags": [],
    "media": [
      {
        "display_url": "pic.twitter.com/3g5fDYX6TR",
        "expanded_url": "https://twitter.com/RealDrGina/status/1333816622725935106/video/1",
        "id": 1333816587577663488,
        "id_str": "1333816587577663488",
        "indices": [
          117,
          140
        ],
        "media_url": "http://pbs.twimg.com/ext_tw_video_thumb/1333816587577663488/pu/img/_EnMavflZ8wNtuz7.jpg",
        "media_url_https": "https://pbs.twimg.com/ext_tw_video_thumb/1333816587577663488/pu/img/_EnMavflZ8wNtuz7.jpg",
        "sizes": {
          "large": {
            "h": 720,
            "resize": "fit",
            "w": 1280
          },
          "medium": {
            "h": 675,
            "resize": "fit",
            "w": 1200
          },
          "small": {
            "h": 383,
            "resize": "fit",
            "w": 680
          },
          "thumb": {
            "h": 150,
            "resize": "crop",
            "w": 150
          }
        },
        "source_status_id": 1333816622725935106,
        "source_status_id_str": "1333816622725935106",
        "source_user_id": 20118767,
        "source_user_id_str": "20118767",
        "type": "photo",
        "url": "https://t.co/3g5fDYX6TR"
      }
    ],
    "symbols": [],
    "urls": [],
    "user_mentions": [
      {
        "id": 20118767,
        "id_str": "20118767",
        "indices": [
          1,
          12
        ],
        "name": "Dr. Gina - Real America\u2019s Voice (RAV-TV) News",
        "screen_name": "RealDrGina"
      },
      {
        "id": 935942321756966912,
        "id_str": "935942321756966912",
        "indices": [
          53,
          65
        ],
        "name": "Real America's Voice (RAV)",
        "screen_name": "RealAmVoice"
      }
    ]
  },
  "extended_entities": {
    "media": [
      {
        "additional_media_info": {
          "monetizable": false,
          "source_user": {
            "contributors_enabled": false,
            "created_at": "Thu Feb 05 03:51:40 +0000 2009",
            "default_profile": false,
            "default_profile_image": false,
            "description": "Senior Anchor & President (Elect?\ud83d\ude43)of Programming, @RealAmVoice (RAV-TV) @JustTheNews #mama \ud83d\udc9e #Jesus #Adoption #DownSyndrome \ud83d\udc3erescue | E/INTJ \ud83c\uddfa\ud83c\uddf8\ud83c\uddee\ud83c\uddf1",
            "entities": {
              "description": {
                "urls": []
              },
              "url": {
                "urls": [
                  {
                    "display_url": "DrGinaLoudon.com",
                    "expanded_url": "http://DrGinaLoudon.com",
                    "indices": [
                      0,
                      23
                    ],
                    "url": "https://t.co/k25a1UsJu1"
                  }
                ]
              }
            },
            "favourites_count": 58393,
            "follow_request_sent": false,
            "followers_count": 235742,
            "following": false,
            "friends_count": 38539,
            "geo_enabled": true,
            "has_extended_profile": true,
            "id": 20118767,
            "id_str": "20118767",
            "is_translation_enabled": false,
            "is_translator": false,
            "lang": null,
            "listed_count": 1255,
            "location": "\ud83c\uddfa\ud83c\uddf8",
            "name": "Dr. Gina - Real America\u2019s Voice (RAV-TV) News",
            "notifications": false,
            "profile_background_color": "07090B",
            "profile_background_image_url": "http://abs.twimg.com/images/themes/theme9/bg.gif",
            "profile_background_image_url_https": "https://abs.twimg.com/images/themes/theme9/bg.gif",
            "profile_background_tile": false,
            "profile_banner_url": "https://pbs.twimg.com/profile_banners/20118767/1524127525",
            "profile_image_url": "http://pbs.twimg.com/profile_images/1191034563138592769/vIuGS51A_normal.jpg",
            "profile_image_url_https": "https://pbs.twimg.com/profile_images/1191034563138592769/vIuGS51A_normal.jpg",
            "profile_link_color": "DD2E44",
            "profile_sidebar_border_color": "000000",
            "profile_sidebar_fill_color": "C9C9C9",
            "profile_text_color": "1C1F23",
            "profile_use_background_image": true,
            "protected": false,
            "screen_name": "RealDrGina",
            "statuses_count": 56930,
            "time_zone": null,
            "translator_type": "regular",
            "url": "https://t.co/k25a1UsJu1",
            "utc_offset": null,
            "verified": true
          }
        },
        "display_url": "pic.twitter.com/3g5fDYX6TR",
        "expanded_url": "https://twitter.com/RealDrGina/status/1333816622725935106/video/1",
        "id": 1333816587577663488,
        "id_str": "1333816587577663488",
        "indices": [
          117,
          140
        ],
        "media_url": "http://pbs.twimg.com/ext_tw_video_thumb/1333816587577663488/pu/img/_EnMavflZ8wNtuz7.jpg",
        "media_url_https": "https://pbs.twimg.com/ext_tw_video_thumb/1333816587577663488/pu/img/_EnMavflZ8wNtuz7.jpg",
        "sizes": {
          "large": {
            "h": 720,
            "resize": "fit",
            "w": 1280
          },
          "medium": {
            "h": 675,
            "resize": "fit",
            "w": 1200
          },
          "small": {
            "h": 383,
            "resize": "fit",
            "w": 680
          },
          "thumb": {
            "h": 150,
            "resize": "crop",
            "w": 150
          }
        },
        "source_status_id": 1333816622725935106,
        "source_status_id_str": "1333816622725935106",
        "source_user_id": 20118767,
        "source_user_id_str": "20118767",
        "type": "video",
        "url": "https://t.co/3g5fDYX6TR",
        "video_info": {
          "aspect_ratio": [
            16,
            9
          ],
          "duration_millis": 27000,
          "variants": [
            {
              "bitrate": 832000,
              "content_type": "video/mp4",
              "url": "https://video.twimg.com/ext_tw_video/1333816587577663488/pu/vid/640x360/y2NL0qNPllrCHBSh.mp4?tag=10"
            },
            {
              "content_type": "application/x-mpegURL",
              "url": "https://video.twimg.com/ext_tw_video/1333816587577663488/pu/pl/Sr8kDkgpW91bC7v1.m3u8?tag=10"
            },
            {
              "bitrate": 256000,
              "content_type": "video/mp4",
              "url": "https://video.twimg.com/ext_tw_video/1333816587577663488/pu/vid/480x270/zjdB8btWlIW2S2cF.mp4?tag=10"
            },
            {
              "bitrate": 2176000,
              "content_type": "video/mp4",
              "url": "https://video.twimg.com/ext_tw_video/1333816587577663488/pu/vid/1280x720/bGGtnER1bpCV0iFO.mp4?tag=10"
            }
          ]
        }
      }
    ]
  },
  "favorite_count": 74306,
  "favorited": false,
  "full_text": ".@RealDrGina \u2014 Good luck on your new show tonight on @RealAmVoice at 7:00 P.M. Eastern. I know it will be a big hit! https://t.co/3g5fDYX6TR",
  "geo": null,
  "id": 1333922807869284352,
  "id_str": "1333922807869284352",
  "in_reply_to_screen_name": null,
  "in_reply_to_status_id": null,
  "in_reply_to_status_id_str": null,
  "in_reply_to_user_id": null,
  "in_reply_to_user_id_str": null,
  "is_quote_status": false,
  "lang": "en",
  "place": null,
  "possibly_sensitive": false,
  "retweet_count": 14264,
  "retweeted": false,
  "source": "<a href=\"http://twitter.com/download/iphone\" rel=\"nofollow\">Twitter for iPhone</a>",
  "truncated": false,
  "user": {
    "contributors_enabled": false,
    "created_at": "Wed Mar 18 13:46:38 +0000 2009",
    "default_profile": false,
    "default_profile_image": false,
    "description": "45th President of the United States of America\ud83c\uddfa\ud83c\uddf8",
    "entities": {
      "description": {
        "urls": []
      },
      "url": {
        "urls": [
          {
            "display_url": "Vote.DonaldJTrump.com",
            "expanded_url": "http://Vote.DonaldJTrump.com",
            "indices": [
              0,
              23
            ],
            "url": "https://t.co/8f9VFxztEJ"
          }
        ]
      }
    },
    "favourites_count": 6,
    "follow_request_sent": false,
    "followers_count": 88745088,
    "following": true,
    "friends_count": 51,
    "geo_enabled": true,
    "has_extended_profile": false,
    "id": 25073877,
    "id_str": "25073877",
    "is_translation_enabled": true,
    "is_translator": false,
    "lang": null,
    "listed_count": 125656,
    "location": "Washington, DC",
    "name": "Donald J. Trump",
    "notifications": false,
    "profile_background_color": "6D5C18",
    "profile_background_image_url": "http://abs.twimg.com/images/themes/theme1/bg.png",
    "profile_background_image_url_https": "https://abs.twimg.com/images/themes/theme1/bg.png",
    "profile_background_tile": true,
    "profile_banner_url": "https://pbs.twimg.com/profile_banners/25073877/1604214583",
    "profile_image_url": "http://pbs.twimg.com/profile_images/874276197357596672/kUuht00m_normal.jpg",
    "profile_image_url_https": "https://pbs.twimg.com/profile_images/874276197357596672/kUuht00m_normal.jpg",
    "profile_link_color": "1B95E0",
    "profile_sidebar_border_color": "BDDCAD",
    "profile_sidebar_fill_color": "C5CEC0",
    "profile_text_color": "333333",
    "profile_use_background_image": true,
    "protected": false,
    "screen_name": "realDonaldTrump",
    "statuses_count": 58930,
    "time_zone": null,
    "translator_type": "regular",
    "url": "https://t.co/8f9VFxztEJ",
    "utc_offset": null,
    "verified": true
  }
}