{
  "contributors": null,
  "coordinates": null,
  "created_at": "Tue Sep 08 20:14:39 +0000 2020",
  "display_text_range": [
    0,
    51
  ],
  "entities": {
    "hashtags": [],
    "media": [
      {
        "display_url": "pic.twitter.com/B4vcal8lOF",
        "expanded_url": "https://twitter.com/DanScavino/status/1303418877406310429/video/1",
        "id": 1303418155495288836,
        "id_str": "1303418155495288836",
        "indices": [
          28,
          51
        ],
        "media_url": "http://pbs.twimg.com/ext_tw_video_thumb/1303418155495288836/pu/img/34NPOBQmaoztTXGK.jpg",
        "media_url_https": "https://pbs.twimg.com/ext_tw_video_thumb/1303418155495288836/pu/img/34NPOBQmaoztTXGK.jpg",
        "sizes": {
          "large": {
            "h": 720,
            "resize": "fit",
            "w": 1280
          },
          "medium": {
            "h": 675,
            "resize": "fit",
            "w": 1200
          },
          "small": {
            "h": 383,
            "resize": "fit",
            "w": 680
          },
          "thumb": {
            "h": 150,
            "resize": "crop",
            "w": 150
          }
        },
        "source_status_id": 1303418877406310429,
        "source_status_id_str": "1303418877406310429",
        "source_user_id": 620571475,
        "source_user_id_str": "620571475",
        "type": "photo",
        "url": "https://t.co/B4vcal8lOF"
      }
    ],
    "symbols": [],
    "urls": [],
    "user_mentions": []
  },
  "extended_entities": {
    "media": [
      {
        "additional_media_info": {
          "monetizable": false,
          "source_user": {
            "contributors_enabled": false,
            "created_at": "Thu Jun 28 02:45:39 +0000 2012",
            "default_profile": false,
            "default_profile_image": false,
            "description": "",
            "entities": {
              "description": {
                "urls": []
              }
            },
            "favourites_count": 2876,
            "follow_request_sent": false,
            "followers_count": 946870,
            "following": false,
            "friends_count": 698,
            "geo_enabled": true,
            "has_extended_profile": false,
            "id": 620571475,
            "id_str": "620571475",
            "is_translation_enabled": false,
            "is_translator": false,
            "lang": null,
            "listed_count": 3970,
            "location": "",
            "name": "Dan Scavino\ud83c\uddfa\ud83c\uddf8\ud83e\udd85",
            "notifications": false,
            "profile_background_color": "131516",
            "profile_background_image_url": "http://abs.twimg.com/images/themes/theme1/bg.png",
            "profile_background_image_url_https": "https://abs.twimg.com/images/themes/theme1/bg.png",
            "profile_background_tile": true,
            "profile_banner_url": "https://pbs.twimg.com/profile_banners/620571475/1596333141",
            "profile_image_url": "http://pbs.twimg.com/profile_images/1284244858677473280/eWVs2LuX_normal.jpg",
            "profile_image_url_https": "https://pbs.twimg.com/profile_images/1284244858677473280/eWVs2LuX_normal.jpg",
            "profile_link_color": "1B95E0",
            "profile_sidebar_border_color": "000000",
            "profile_sidebar_fill_color": "000000",
            "profile_text_color": "000000",
            "profile_use_background_image": true,
            "protected": false,
            "screen_name": "DanScavino",
            "statuses_count": 11260,
            "time_zone": null,
            "translator_type": "none",
            "url": null,
            "utc_offset": null,
            "verified": true
          }
        },
        "display_url": "pic.twitter.com/B4vcal8lOF",
        "expanded_url": "https://twitter.com/DanScavino/status/1303418877406310429/video/1",
        "id": 1303418155495288836,
        "id_str": "1303418155495288836",
        "indices": [
          28,
          51
        ],
        "media_url": "http://pbs.twimg.com/ext_tw_video_thumb/1303418155495288836/pu/img/34NPOBQmaoztTXGK.jpg",
        "media_url_https": "https://pbs.twimg.com/ext_tw_video_thumb/1303418155495288836/pu/img/34NPOBQmaoztTXGK.jpg",
        "sizes": {
          "large": {
            "h": 720,
            "resize": "fit",
            "w": 1280
          },
          "medium": {
            "h": 675,
            "resize": "fit",
            "w": 1200
          },
          "small": {
            "h": 383,
            "resize": "fit",
            "w": 680
          },
          "thumb": {
            "h": 150,
            "resize": "crop",
            "w": 150
          }
        },
        "source_status_id": 1303418877406310429,
        "source_status_id_str": "1303418877406310429",
        "source_user_id": 620571475,
        "source_user_id_str": "620571475",
        "type": "video",
        "url": "https://t.co/B4vcal8lOF",
        "video_info": {
          "aspect_ratio": [
            16,
            9
          ],
          "duration_millis": 25663,
          "variants": [
            {
              "bitrate": 256000,
              "content_type": "video/mp4",
              "url": "https://video.twimg.com/ext_tw_video/1303418155495288836/pu/vid/480x270/I_fKlvUtFqsaic26.mp4?tag=10"
            },
            {
              "content_type": "application/x-mpegURL",
              "url": "https://video.twimg.com/ext_tw_video/1303418155495288836/pu/pl/iqyQewdl6nKeK2wf.m3u8?tag=10"
            },
            {
              "bitrate": 832000,
              "content_type": "video/mp4",
              "url": "https://video.twimg.com/ext_tw_video/1303418155495288836/pu/vid/640x360/1KEM0b96XJqoZGBC.mp4?tag=10"
            },
            {
              "bitrate": 2176000,
              "content_type": "video/mp4",
              "url": "https://video.twimg.com/ext_tw_video/1303418155495288836/pu/vid/1280x720/WX1kGdFo0FKoWmri.mp4?tag=10"
            }
          ]
        }
      }
    ]
  },
  "favorite_count": 131717,
  "favorited": false,
  "full_text": "Thank you Jupiter, Florida! https://t.co/B4vcal8lOF",
  "geo": null,
  "id": 1303426544476581896,
  "id_str": "1303426544476581896",
  "in_reply_to_screen_name": null,
  "in_reply_to_status_id": null,
  "in_reply_to_status_id_str": null,
  "in_reply_to_user_id": null,
  "in_reply_to_user_id_str": null,
  "is_quote_status": false,
  "lang": "en",
  "place": null,
  "possibly_sensitive": false,
  "retweet_count": 29418,
  "retweeted": false,
  "source": "<a href=\"http://twitter.com/download/iphone\" rel=\"nofollow\">Twitter for iPhone</a>",
  "truncated": false,
  "user": {
    "contributors_enabled": false,
    "created_at": "Wed Mar 18 13:46:38 +0000 2009",
    "default_profile": false,
    "default_profile_image": false,
    "description": "45th President of the United States of America\ud83c\uddfa\ud83c\uddf8",
    "entities": {
      "description": {
        "urls": []
      },
      "url": {
        "urls": [
          {
            "display_url": "Instagram.com/realDonaldTrump",
            "expanded_url": "http://www.Instagram.com/realDonaldTrump",
            "indices": [
              0,
              23
            ],
            "url": "https://t.co/OMxB0x7xC5"
          }
        ]
      }
    },
    "favourites_count": 4,
    "follow_request_sent": false,
    "followers_count": 85836389,
    "following": true,
    "friends_count": 50,
    "geo_enabled": true,
    "has_extended_profile": false,
    "id": 25073877,
    "id_str": "25073877",
    "is_translation_enabled": true,
    "is_translator": false,
    "lang": null,
    "listed_count": 119283,
    "location": "Washington, DC",
    "name": "Donald J. Trump",
    "notifications": false,
    "profile_background_color": "6D5C18",
    "profile_background_image_url": "http://abs.twimg.com/images/themes/theme1/bg.png",
    "profile_background_image_url_https": "https://abs.twimg.com/images/themes/theme1/bg.png",
    "profile_background_tile": true,
    "profile_banner_url": "https://pbs.twimg.com/profile_banners/25073877/1595058372",
    "profile_image_url": "http://pbs.twimg.com/profile_images/874276197357596672/kUuht00m_normal.jpg",
    "profile_image_url_https": "https://pbs.twimg.com/profile_images/874276197357596672/kUuht00m_normal.jpg",
    "profile_link_color": "1B95E0",
    "profile_sidebar_border_color": "BDDCAD",
    "profile_sidebar_fill_color": "C5CEC0",
    "profile_text_color": "333333",
    "profile_use_background_image": true,
    "protected": false,
    "screen_name": "realDonaldTrump",
    "statuses_count": 55668,
    "time_zone": null,
    "translator_type": "regular",
    "url": "https://t.co/OMxB0x7xC5",
    "utc_offset": null,
    "verified": true
  }
}